[{"wp_inactive_widgets":["tag_cloud-2","recent-comments-2","pages-2","archives-2","calendar-2","search-2","nav_menu-2","meta-2","text-5","recent-posts-2"],"main-sidebar":["categories-2","my_postwidget-2","my-recent-comments-2"],"footer-sidebar-1":["text-2"],"footer-sidebar-2":["text-3"],"footer-sidebar-3":["text-4"]},{"tag_cloud":{"2":{"title":"Tag Cloud","taxonomy":"post_tag"},"_multiwidget":1},"recent-comments":{"2":{"title":"Recent Comments","number":5},"_multiwidget":1},"pages":{"2":{"title":"Pages","sortby":"menu_order","exclude":""},"_multiwidget":1},"archives":{"2":{"title":"Archives","count":0,"dropdown":0},"_multiwidget":1},"calendar":{"2":{"title":"Calendar"},"_multiwidget":1},"search":{"2":{"title":"Search"},"_multiwidget":1},"nav_menu":{"2":{"title":"Main Menu","nav_menu":24,"nav_menu_slug":"header-menu"},"_multiwidget":1},"meta":{"2":{"title":"Meta"},"_multiwidget":1},"text":{"5":{"title":"Pellentesque","text":"Pellentesque fermentum tristique sollicitudin. Pellentesque volutpat sit amet odio vel consectetur. Interdum et malesuada fames ac ante ipsum primis in faucibus. Curabitur scelerisque porta vehicula. Duis dui metus, bibendum eget commodo nec, convallis vel mauris.","filter":false},"2":{"title":"Testimonials","text":"[recenttesti num=\"1\" thumb=\"false\" excerpt_count=\"25\"]\r\n[button text=\"more testimonials\" link=\"our-staff\/testi\" style=\"primary\" size=\"normal\" target=\"_self\" display=\"inline\" icon=\"no\"] ","filter":false},"3":{"title":"Our services","text":"[row_in] [span2]\r\n<ul>\r\n  <li><a href=\"#\">wellness exam<\/a><\/li>\r\n  <li><a href=\"#\">puppy wellness<\/a><\/li>\r\n  <li><a href=\"#\">kitten wellness<\/a><\/li>\r\n  <li><a href=\"#\">Laboratory services<\/a><\/li>\r\n  <li><a href=\"#\">X-rays (radiology)<\/a><\/li>\r\n  <li><a href=\"#\">ultrasonography<\/a><\/li>\r\n<\/ul>\r\n[\/span2] [span2]\r\n<ul>\r\n  <li><a href=\"#\">dental cleaning<\/a><\/li>\r\n  <li><a href=\"#\">flea control<\/a><\/li>\r\n  <li><a href=\"#\">Exotic pet care<\/a><\/li>\r\n  <li><a href=\"#\">emergency<\/a><\/li>\r\n  <li><a href=\"#\">miscellaneous<\/a><\/li>\r\n  <li><a href=\"#\">Cremation<\/a><\/li>\r\n<\/ul>\r\n[\/span2] [\/row_in]\r\n[button text=\"read more\" link=\"portfolio\" style=\"primary\" size=\"normal\" target=\"_self\" display=\"inline\" icon=\"no\"] ","filter":false},"4":{"title":"PetClinic","text":"<p>28 Jackson Blvd Ste 1020 <br> Chicago <br> IL 60604-2340<\/p>\r\n<em><a href=\"contacts\">info@demolink.org<\/a><\/em>\r\n<strong><a href=\"contacts\">on-line form<\/a><\/strong>","filter":false},"_multiwidget":1},"recent-posts":{"2":{"title":"Recent Posts","number":5,"show_date":false},"_multiwidget":1},"categories":{"2":{"title":"Categories","count":0,"hierarchical":0,"dropdown":0},"_multiwidget":1},"my_postwidget":{"2":{"title":"Recent posts","category":"","post_format":"post-format-standard","sort_by":"date","count":"2","excerpt_count":"10","linktext":"","linkurl":""},"_multiwidget":1},"my-recent-comments":{"2":{"title":"Recent Comments","comments_count":"3","avatar_size":"64","display_author_name":"on","display_avatar":"on","display_date":"on","display_post_title":null,"meta_format":"none"},"_multiwidget":1}},[]]